invenio_indexer/__init__.py
invenio_indexer/api.py
invenio_indexer/cli.py
invenio_indexer/config.py
invenio_indexer/ext.py
invenio_indexer/proxies.py
invenio_indexer/registry.py
invenio_indexer/signals.py
invenio_indexer/tasks.py
invenio_indexer/utils.py
invenio_indexer-3.1.0.dist-info/licenses/AUTHORS.rst
invenio_indexer-3.1.0.dist-info/licenses/LICENSE
invenio_indexer-3.1.0.dist-info/METADATA
invenio_indexer-3.1.0.dist-info/WHEEL
invenio_indexer-3.1.0.dist-info/entry_points.txt
invenio_indexer-3.1.0.dist-info/top_level.txt
invenio_indexer-3.1.0.dist-info/RECORD
