Metadata-Version: 2.4
Name: invenio-indexer
Version: 3.1.0
Summary: "Record indexer for Invenio."
Home-page: https://github.com/inveniosoftware/invenio-indexer
Author: CERN
Author-email: info@inveniosoftware.org
License: MIT
Keywords: invenio search indexing
Platform: any
Classifier: Development Status :: 5 - Production/Stable
Requires-Python: >=3.7
License-File: LICENSE
License-File: AUTHORS.rst
Requires-Dist: invenio-db<3.0.0,>=2.0.0
Requires-Dist: invenio-pidstore<3.0.0,>=2.0.0
Requires-Dist: invenio-records<4.0.0,>=3.0.0
Requires-Dist: pytz>=2016.4
Provides-Extra: tests
Requires-Dist: pytest-black-ng>=0.4.0; extra == "tests"
Requires-Dist: attrs>=17.4.0; extra == "tests"
Requires-Dist: pytest-invenio<4.0.0,>=3.0.0; extra == "tests"
Requires-Dist: redis>=3.4.0; extra == "tests"
Requires-Dist: sphinx>=4.5; extra == "tests"
Provides-Extra: elasticsearch7
Requires-Dist: elasticsearch<7.14.0,>=7.5.0; extra == "elasticsearch7"
Requires-Dist: invenio-search[elasticsearch7]<4.0.0,>=3.0.0; extra == "elasticsearch7"
Provides-Extra: opensearch1
Requires-Dist: invenio-search[opensearch1]<4.0.0,>=3.0.0; extra == "opensearch1"
Provides-Extra: opensearch2
Requires-Dist: invenio-search[opensearch2]<4.0.0,>=3.0.0; extra == "opensearch2"
Provides-Extra: docs
Dynamic: license-file
